sassquatch/__about__.py
sassquatch/__init__.py
sassquatch/build.py
sassquatch/core.py
sassquatch/vendor/dart-sass/sass
sassquatch/vendor/dart-sass/src/LICENSE
sassquatch/vendor/dart-sass/src/dart
sassquatch/vendor/dart-sass/src/sass.snapshot
sassquatch-0.1.1.dist-info/METADATA
sassquatch-0.1.1.dist-info/WHEEL
sassquatch-0.1.1.dist-info/entry_points.txt
sassquatch-0.1.1.dist-info/top_level.txt
sassquatch-0.1.1.dist-info/RECORD
