Metadata-Version: 2.4
Name: sassquatch
Version: 0.1.1
Summary: Dart Sass (Embedded) in Python
Author-email: Robin van der Noord <robinvandernoord@gmail.com>
Requires-Python: >=3.12
Requires-Dist: sleazy
Provides-Extra: dev
Requires-Dist: pytest; extra == "dev"
